py_bugs_open_ai/__init__.py
py_bugs_open_ai/cli.py
py_bugs_open_ai/constants.py
py_bugs_open_ai/diff.py
py_bugs_open_ai/open_ai_client.py
py_bugs_open_ai/py_bugs_open_ai.py
py_bugs_open_ai/models/__init__.py
py_bugs_open_ai/models/base.py
py_bugs_open_ai/models/examples.py
py_bugs_open_ai/models/open_ai.py
py_bugs_open_ai-0.1.3.dist-info/LICENSE
py_bugs_open_ai-0.1.3.dist-info/METADATA
py_bugs_open_ai-0.1.3.dist-info/WHEEL
py_bugs_open_ai-0.1.3.dist-info/entry_points.txt
py_bugs_open_ai-0.1.3.dist-info/top_level.txt
py_bugs_open_ai-0.1.3.dist-info/RECORD
