Metadata-Version: 2.1
Name: py-bugs-open-ai
Version: 0.1.3
Summary: A utility to help use OpenAI to find bugs in large projects or git diffs in python code.  Makes heavy use of caching to save time/money
Home-page: https://github.com/valmikirao/py_bugs_open_ai
Author: Valmiki Rao
Author-email: valmikirao@gmail.com
License: GNU General Public License v3
Keywords: py_bugs_open_ai
Classifier: Development Status :: 2 - Pre-Alpha
Classifier: Intended Audience :: Developers
Classifier: License :: OSI Approved :: GNU General Public License v3 (GPLv3)
Classifier: Natural Language :: English
Classifier: Programming Language :: Python :: 3
Classifier: Programming Language :: Python :: 3.8
Classifier: Programming Language :: Python :: 3.9
Classifier: Programming Language :: Python :: 3.10
Classifier: Programming Language :: Python :: 3.11
Requires-Python: >=3.8
License-File: LICENSE
Requires-Dist: Click (<9.0.0,>=8.1.3)
Requires-Dist: pydantic (<2.0.0,>=1.10.7)
Requires-Dist: diskcache (<6.0.0,>=5.6.1)
Requires-Dist: openai[embeddings] (<1.0.0,>=0.27.4)
Requires-Dist: PyYAML (<7.0.0,>=6.0.0)
Requires-Dist: tiktoken (<1.0.0,>=0.3.3)
Requires-Dist: tenacity (<9.0.0,>=8.2.2)
